codesdevs_log_analyzer/__init__.py
codesdevs_log_analyzer/cli.py
codesdevs_log_analyzer/demo.py
codesdevs_log_analyzer/models.py
codesdevs_log_analyzer/server.py
codesdevs_log_analyzer/analyzers/__init__.py
codesdevs_log_analyzer/analyzers/correlator.py
codesdevs_log_analyzer/analyzers/error_extractor.py
codesdevs_log_analyzer/analyzers/log_watcher.py
codesdevs_log_analyzer/analyzers/multi_file.py
codesdevs_log_analyzer/analyzers/pattern_matcher.py
codesdevs_log_analyzer/analyzers/pattern_suggester.py
codesdevs_log_analyzer/analyzers/query_translator.py
codesdevs_log_analyzer/analyzers/recommendation_engine.py
codesdevs_log_analyzer/analyzers/sensitive_detector.py
codesdevs_log_analyzer/analyzers/summarizer.py
codesdevs_log_analyzer/analyzers/trace_extractor.py
codesdevs_log_analyzer/parsers/__init__.py
codesdevs_log_analyzer/parsers/apache.py
codesdevs_log_analyzer/parsers/base.py
codesdevs_log_analyzer/parsers/docker.py
codesdevs_log_analyzer/parsers/generic.py
codesdevs_log_analyzer/parsers/java.py
codesdevs_log_analyzer/parsers/jsonl.py
codesdevs_log_analyzer/parsers/kubernetes.py
codesdevs_log_analyzer/parsers/python_log.py
codesdevs_log_analyzer/parsers/syslog.py
codesdevs_log_analyzer/utils/__init__.py
codesdevs_log_analyzer/utils/file_handler.py
codesdevs_log_analyzer/utils/formatters.py
codesdevs_log_analyzer/utils/time_utils.py
codesdevs_log_analyzer-0.5.0.dist-info/METADATA
codesdevs_log_analyzer-0.5.0.dist-info/WHEEL
codesdevs_log_analyzer-0.5.0.dist-info/entry_points.txt
codesdevs_log_analyzer-0.5.0.dist-info/licenses/LICENSE
codesdevs_log_analyzer-0.5.0.dist-info/RECORD
