Metadata-Version: 2.4
Name: codesdevs-log-analyzer
Version: 0.5.0
Summary: MCP server for intelligent log file analysis and debugging assistance
Project-URL: Homepage, https://github.com/Fato07/log-analyzer-mcp
Project-URL: Repository, https://github.com/Fato07/log-analyzer-mcp
Project-URL: Issues, https://github.com/Fato07/log-analyzer-mcp/issues
Author-email: Fathin <fathin@codesdevs.com>
License: MIT
License-File: LICENSE
Keywords: ai,claude,debugging,log-analysis,mcp
Classifier: Development Status :: 4 - Beta
Classifier: Intended Audience :: Developers
Classifier: License :: OSI Approved :: MIT License
Classifier: Programming Language :: Python :: 3
Classifier: Programming Language :: Python :: 3.10
Classifier: Programming Language :: Python :: 3.11
Classifier: Programming Language :: Python :: 3.12
Classifier: Topic :: Software Development :: Debuggers
Classifier: Topic :: System :: Logging
Requires-Python: >=3.10
Requires-Dist: chardet>=5.0.0
Requires-Dist: mcp>=1.0.0
Requires-Dist: pydantic>=2.0.0
Requires-Dist: python-dateutil>=2.8.0
Requires-Dist: rich>=13.0.0
Provides-Extra: dev
Requires-Dist: mypy>=1.0.0; extra == 'dev'
Requires-Dist: pytest-asyncio>=0.21.0; extra == 'dev'
Requires-Dist: pytest-cov>=4.0.0; extra == 'dev'
Requires-Dist: pytest>=7.0.0; extra == 'dev'
Requires-Dist: ruff>=0.1.0; extra == 'dev'
Requires-Dist: types-python-dateutil>=2.8.0; extra == 'dev'
